nautobot_chatops/__init__.py
nautobot_chatops/admin.py
nautobot_chatops/api/__init__.py
nautobot_chatops/api/serializers.py
nautobot_chatops/api/urls.py
nautobot_chatops/api/views/__init__.py
nautobot_chatops/api/views/generic.py
nautobot_chatops/api/views/lookup.py
nautobot_chatops/api/views/mattermost.py
nautobot_chatops/api/views/ms_teams.py
nautobot_chatops/api/views/slack.py
nautobot_chatops/api/views/webex.py
nautobot_chatops/app-config-schema.json
nautobot_chatops/banner.py
nautobot_chatops/choices.py
nautobot_chatops/constants.py
nautobot_chatops/dispatchers/__init__.py
nautobot_chatops/dispatchers/adaptive_cards.py
nautobot_chatops/dispatchers/base.py
nautobot_chatops/dispatchers/mattermost.py
nautobot_chatops/dispatchers/ms_teams.py
nautobot_chatops/dispatchers/slack.py
nautobot_chatops/dispatchers/webex.py
nautobot_chatops/filters.py
nautobot_chatops/forms.py
nautobot_chatops/integrations/__init__.py
nautobot_chatops/integrations/aci/__init__.py
nautobot_chatops/integrations/aci/aci.py
nautobot_chatops/integrations/aci/utils.py
nautobot_chatops/integrations/aci/worker.py
nautobot_chatops/integrations/ansible/__init__.py
nautobot_chatops/integrations/ansible/tower.py
nautobot_chatops/integrations/ansible/worker.py
nautobot_chatops/integrations/cloudvision/__init__.py
nautobot_chatops/integrations/cloudvision/cvpgrpcutils.py
nautobot_chatops/integrations/cloudvision/utils.py
nautobot_chatops/integrations/cloudvision/worker.py
nautobot_chatops/integrations/grafana/__init__.py
nautobot_chatops/integrations/grafana/api/__init__.py
nautobot_chatops/integrations/grafana/api/serializers.py
nautobot_chatops/integrations/grafana/api/urls.py
nautobot_chatops/integrations/grafana/api/views.py
nautobot_chatops/integrations/grafana/diffsync/models.py
nautobot_chatops/integrations/grafana/diffsync/sync.py
nautobot_chatops/integrations/grafana/django1.json
nautobot_chatops/integrations/grafana/exceptions.py
nautobot_chatops/integrations/grafana/filters.py
nautobot_chatops-3.3.0.dist-info/LICENSE
nautobot_chatops-3.3.0.dist-info/METADATA
nautobot_chatops-3.3.0.dist-info/NOTICE
nautobot_chatops-3.3.0.dist-info/WHEEL
nautobot_chatops-3.3.0.dist-info/entry_points.txt
nautobot_chatops-3.3.0.dist-info/RECORD
