Metadata-Version: 2.3
Name: nautobot-chatops
Version: 3.3.0
Summary: A app providing chatbot capabilities for Nautobot
License: Apache-2.0
Keywords: nautobot,nautobot-app,nautobot-plugin
Author: Network to Code, LLC
Author-email: opensource@networktocode.com
Requires-Python: >=3.10,<3.13
Classifier: Development Status :: 5 - Production/Stable
Classifier: Intended Audience :: Developers
Classifier: License :: OSI Approved :: Apache Software License
Classifier: Programming Language :: Python :: 3
Classifier: Programming Language :: Python :: 3.10
Classifier: Programming Language :: Python :: 3.11
Classifier: Programming Language :: Python :: 3.12
Provides-Extra: aci
Provides-Extra: all
Provides-Extra: ansible
Provides-Extra: aristacv
Provides-Extra: grafana
Provides-Extra: ipfabric
Provides-Extra: meraki
Provides-Extra: panorama
Provides-Extra: slurpit
Requires-Dist: Markdown (!=3.3.5)
Requires-Dist: PyJWT (>=2.1.0,<3.0.0)
Requires-Dist: PyYAML (>=6.0,<7.0) ; extra == "all" or extra == "ansible"
Requires-Dist: aiodns (>=1.0,<2.0)
Requires-Dist: aiohttp (>=3.7.3,<4.0.0)
Requires-Dist: asgiref (>=3.4.1,<4.0.0)
Requires-Dist: certifi (>=2021.5.30) ; extra == "all" or extra == "aristacv"
Requires-Dist: cloudvision (>=1.1,<2.0) ; extra == "all" or extra == "aristacv"
Requires-Dist: cvprac (>=1.0.6,<2.0.0) ; extra == "all" or extra == "aristacv"
Requires-Dist: defusedxml (>=0.7.1,<0.8.0) ; extra == "all" or extra == "panorama"
Requires-Dist: diffsync (>=1.3.0,<2.0.0) ; extra == "all" or extra == "grafana"
Requires-Dist: ipaddr (>=2.2.0,<3.0.0) ; extra == "all" or extra == "panorama"
Requires-Dist: ipfabric (>=6.6.2,<7.0.0) ; extra == "all" or extra == "ipfabric"
Requires-Dist: isodate (>=0.6.1,<0.7.0) ; extra == "all" or extra == "grafana"
Requires-Dist: meraki (>=1.7.2,<=1.45.0) ; extra == "all" or extra == "meraki"
Requires-Dist: nautobot (>=2.4.20,<3.0.0)
Requires-Dist: nautobot-capacity-metrics (>=3.0.0,<4.0.0)
Requires-Dist: netmiko (>=4.0.0,<5.0.0) ; extra == "all" or extra == "panorama"
Requires-Dist: netutils (>=1.1.0,<2.0.0) ; extra == "all" or extra == "ipfabric" or extra == "panorama"
Requires-Dist: pan-os-python (>=1.3.0,<2.0.0) ; extra == "all" or extra == "panorama"
Requires-Dist: prettytable (>=2.1.0,<3.0.0) ; extra == "all" or extra == "aci"
Requires-Dist: protobuf (>=3.17,<4.0) ; extra == "all" or extra == "aristacv"
Requires-Dist: pydantic (>=2.0.0,<3.0.0) ; extra == "all" or extra == "grafana"
Requires-Dist: requests (>=2.25.1)
Requires-Dist: schema-enforcer (>=1.5.0,<2.0.0) ; extra == "all" or extra == "grafana"
Requires-Dist: slack-sdk (>=3.19.0,<4.0.0)
Requires-Dist: slurpit-sdk (>=0.9.55) ; (python_version >= "3.8" and python_full_version <= "3.13.0") and (extra == "all" or extra == "slurpit")
Requires-Dist: termcolor (>=3.2.0,<4.0.0) ; extra == "all" or extra == "grafana"
Requires-Dist: texttable (>=1.6.2,<2.0.0)
Requires-Dist: webexteamssdk (>=1.3,<2.0)
Project-URL: Documentation, https://docs.nautobot.com/projects/chatops/en/latest/
Project-URL: Homepage, https://github.com/nautobot/nautobot-app-chatops
Project-URL: Repository, https://github.com/nautobot/nautobot-app-chatops
